{
    "explorer.icon.enableNerdfont": true,
    "explorer.icon.source": "vim-devicons",
    "inlayHint.enable": false,
    "go.checkForUpdates": "false",
    "suggest.autoTrigger": "always",
    "suggest.noselect": false,
    "suggest.timeout": 5000,
    "suggest.virtualText": false,
    "suggest.selection": "recentlyUsed",
    "suggest.detailField": "preview",
    "suggest.minTriggerInputLength": 1,
    "suggest.floatConfig": {
        "border": true,
        "highlight": "CocFloating",
        "borderhighlight": "CocFloating",
        "rounded": true
    },
    "diagnostic.floatConfig": {
        "border": true,
        "borderhighlight": "CocFloating",
        "highlight": "CocFloating",
        "focusable": true,
        "rounded": true
    },
    "hover.floatConfig": {
        "border": true,
        "borderhighlight": "CocFloating",
        "highlight": "CocFloating",
        "focusable": true,
        "title": "🎈",
        "rounded": true
    },
    "coc.preferences.extensionUpdateCheck": "never",
    "explorer.focus": true,
    "explorer.previewAction.onHover": "labeling",
    "Lua.telemetry.enable": true,
    "snippets.ultisnips.pythonPrompt": false,
    "markdown-preview-enhanced.previewTheme": "vue.css"
}
